{"config": {"view": {"continuousWidth": 400, "continuousHeight": 300}}, "layer": [{"mark": {"type": "line", "interpolate": "basis"}, "encoding": {"color": {"value": "#1F955C"}, "x": {"field": "Datum", "title": "D\u00e1tum", "type": "temporal"}, "y": {"field": "honos", "scale": {"domainMax": 1025.0, "domainMin": 924.0}, "title": "F\u0151", "type": "quantitative"}}}, {"mark": "point", "encoding": {"opacity": {"value": 0}, "x": {"field": "Datum", "type": "temporal"}}, "selection": {"selector6855": {"type": "single", "nearest": true, "on": "mouseover", "fields": ["Datum"], "empty": "none"}}}, {"mark": "point", "encoding": {"color": {"value": "#1F955C"}, "opacity": {"condition": {"value": 1, "selection": "selector6855"}, "value": 0}, "x": {"field": "Datum", "title": "D\u00e1tum", "type": "temporal"}, "y": {"field": "honos", "scale": {"domainMax": 1025.0, "domainMin": 924.0}, "title": "F\u0151", "type": "quantitative"}}}, {"mark": {"type": "rule", "color": "gray"}, "encoding": {"x": {"field": "Datum", "title": "D\u00e1tum", "type": "temporal"}}, "transform": [{"filter": {"selection": "selector6855"}}]}, {"mark": {"type": "text", "align": "left", "dx": 5, "dy": -5}, "encoding": {"color": {"value": "#1F955C"}, "text": {"condition": {"field": "honos", "type": "quantitative", "selection": "selector6855"}, "value": " "}, "x": {"field": "Datum", "title": "D\u00e1tum", "type": "temporal"}, "y": {"field": "honos", "scale": {"domainMax": 1025.0, "domainMin": 924.0}, "title": "F\u0151", "type": "quantitative"}}}], "data": {"name": "data-5e1b116ec507f3bc73f713639fdddac7"}, "height": 50, "padding": {"left": 5, "top": 5, "right": 50, "bottom": 5}, "title": ["Miskolc, 083. sz\u00e1m\u00fa szavaz\u00f3k\u00f6r", "3531 Miskolc, Gy\u0151ri kapu 48-50. (Mc-i V\u00e1rosgazda Nonprofit Kft.)", "BORSOD-ABA\u00daJ-ZEMPL\u00c9N megye, 02. sz\u00e1m\u00fa OEVK"], "width": 600, "$schema": "https://vega.github.io/schema/vega-lite/v4.17.0.json", "datasets": {"data-5e1b116ec507f3bc73f713639fdddac7": [{"sorszam": 83, "szk_nev": "Miskolc, 083. sz\u00e1m\u00fa szavaz\u00f3k\u00f6r", "evk": 2, "evk_nev": "BORSOD-ABA\u00daJ-ZEMPL\u00c9N megye, 02. sz\u00e1m\u00fa OEVK", "cim": "3531 Miskolc, Gy\u0151ri kapu 48-50. (Mc-i V\u00e1rosgazda Nonprofit Kft.)", "akadaly": "N", "szamlKijelolt": "N", "atjKijelolt": "N", "telepSzintu": "N", "indulo": 974, "honos": 974, "osszesen": 974, "maz": 5, "taz": 202, "version": 1131852, "megnev": "Miskolc", "filename": "Miskolc", "Datum": "2022-01-13T18:52:00"}, {"sorszam": 83, "szk_nev": "Miskolc, 083. sz\u00e1m\u00fa szavaz\u00f3k\u00f6r", "evk": 2, "evk_nev": "BORSOD-ABA\u00daJ-ZEMPL\u00c9N megye, 02. sz\u00e1m\u00fa OEVK", "cim": "3531 Miskolc, Gy\u0151ri kapu 48-50. (Mc-i V\u00e1rosgazda Nonprofit Kft.)", "akadaly": "N", "szamlKijelolt": "N", "atjKijelolt": "N", "telepSzintu": "N", "indulo": 974, "honos": 975, "osszesen": 975, "maz": 5, "taz": 202, "version": 1161935, "megnev": "Miskolc", "filename": "Miskolc", "Datum": "2022-01-16T19:35:00"}, {"sorszam": 83, "szk_nev": "Miskolc, 083. sz\u00e1m\u00fa szavaz\u00f3k\u00f6r", "evk": 2, "evk_nev": "BORSOD-ABA\u00daJ-ZEMPL\u00c9N megye, 02. sz\u00e1m\u00fa OEVK", "cim": "3531 Miskolc, Gy\u0151ri kapu 48-50. (Mc-i V\u00e1rosgazda Nonprofit Kft.)", "akadaly": "N", "szamlKijelolt": "N", "atjKijelolt": "N", "telepSzintu": "N", "indulo": 974, "honos": 975, "osszesen": 975, "maz": 5, "taz": 202, "version": 1181335, "megnev": "Miskolc", "filename": "Miskolc", "Datum": "2022-01-18T13:35:00"}, {"sorszam": 83, "szk_nev": "Miskolc, 083. sz\u00e1m\u00fa szavaz\u00f3k\u00f6r", "evk": 2, "evk_nev": "BORSOD-ABA\u00daJ-ZEMPL\u00c9N megye, 02. sz\u00e1m\u00fa OEVK", "cim": "3531 Miskolc, Gy\u0151ri kapu 48-50. (Mc-i V\u00e1rosgazda Nonprofit Kft.)", "akadaly": "N", "szamlKijelolt": "N", "atjKijelolt": "N", "telepSzintu": "N", "indulo": 974, "honos": 975, "osszesen": 975, "maz": 5, "taz": 202, "version": 1182005, "megnev": "Miskolc", "filename": "Miskolc", "Datum": "2022-01-18T20:05:00"}, {"sorszam": 83, "szk_nev": "Miskolc, 083. sz\u00e1m\u00fa szavaz\u00f3k\u00f6r", "evk": 2, "evk_nev": "BORSOD-ABA\u00daJ-ZEMPL\u00c9N megye, 02. sz\u00e1m\u00fa OEVK", "cim": "3531 Miskolc, Gy\u0151ri kapu 48-50. (Mc-i V\u00e1rosgazda Nonprofit Kft.)", "akadaly": "N", "szamlKijelolt": "N", "atjKijelolt": "N", "telepSzintu": "N", "indulo": 974, "honos": 974, "osszesen": 974, "maz": 5, "taz": 202, "version": 1191105, "megnev": "Miskolc", "filename": "Miskolc", "Datum": "2022-01-19T11:05:00"}, {"sorszam": 83, "szk_nev": "Miskolc, 083. sz\u00e1m\u00fa szavaz\u00f3k\u00f6r", "evk": 2, "evk_nev": "BORSOD-ABA\u00daJ-ZEMPL\u00c9N megye, 02. sz\u00e1m\u00fa OEVK", "cim": "3531 Miskolc, Gy\u0151ri kapu 48-50. (Mc-i V\u00e1rosgazda Nonprofit Kft.)", "akadaly": "N", "szamlKijelolt": "N", "atjKijelolt": "N", "telepSzintu": "N", "indulo": 974, "honos": 974, "osszesen": 974, "maz": 5, "taz": 202, "version": 1191935, "megnev": "Miskolc", "filename": "Miskolc", "Datum": "2022-01-19T19:35:00"}, {"sorszam": 83, "szk_nev": "Miskolc, 083. sz\u00e1m\u00fa szavaz\u00f3k\u00f6r", "evk": 2, "evk_nev": "BORSOD-ABA\u00daJ-ZEMPL\u00c9N megye, 02. sz\u00e1m\u00fa OEVK", "cim": "3531 Miskolc, Gy\u0151ri kapu 48-50. (Mc-i V\u00e1rosgazda Nonprofit Kft.)", "akadaly": "N", "szamlKijelolt": "N", "atjKijelolt": "N", "telepSzintu": "N", "indulo": 974, "honos": 974, "osszesen": 974, "maz": 5, "taz": 202, "version": 1201934, "megnev": "Miskolc", "filename": "Miskolc", "Datum": "2022-01-20T19:34:00"}, {"sorszam": 83, "szk_nev": "Miskolc, 083. sz\u00e1m\u00fa szavaz\u00f3k\u00f6r", "evk": 2, "evk_nev": "BORSOD-ABA\u00daJ-ZEMPL\u00c9N megye, 02. sz\u00e1m\u00fa OEVK", "cim": "3531 Miskolc, Gy\u0151ri kapu 48-50. (Mc-i V\u00e1rosgazda Nonprofit Kft.)", "akadaly": "N", "szamlKijelolt": "N", "atjKijelolt": "N", "telepSzintu": "N", "indulo": 974, "honos": 974, "osszesen": 974, "maz": 5, "taz": 202, "version": 1212105, "megnev": "Miskolc", "filename": "Miskolc", "Datum": "2022-01-21T21:05:00"}, {"sorszam": 83, "szk_nev": "Miskolc, 083. sz\u00e1m\u00fa szavaz\u00f3k\u00f6r", "evk": 2, "evk_nev": "BORSOD-ABA\u00daJ-ZEMPL\u00c9N megye, 02. sz\u00e1m\u00fa OEVK", "cim": "3531 Miskolc, Gy\u0151ri kapu 48-50. (Mc-i V\u00e1rosgazda Nonprofit Kft.)", "akadaly": "N", "szamlKijelolt": "N", "atjKijelolt": "N", "telepSzintu": "N", "indulo": 974, "honos": 974, "osszesen": 974, "maz": 5, "taz": 202, "version": 1220905, "megnev": "Miskolc", "filename": "Miskolc", "Datum": "2022-01-22T09:05:00"}, {"sorszam": 83, "szk_nev": "Miskolc, 083. sz\u00e1m\u00fa szavaz\u00f3k\u00f6r", "evk": 2, "evk_nev": "BORSOD-ABA\u00daJ-ZEMPL\u00c9N megye, 02. sz\u00e1m\u00fa OEVK", "cim": "3531 Miskolc, Gy\u0151ri kapu 48-50. (Mc-i V\u00e1rosgazda Nonprofit Kft.)", "akadaly": "N", "szamlKijelolt": "N", "atjKijelolt": "N", "telepSzintu": "N", "indulo": 974, "honos": 974, "osszesen": 974, "maz": 5, "taz": 202, "version": 1222105, "megnev": "Miskolc", "filename": "Miskolc", "Datum": "2022-01-22T21:05:00"}]}}